questioner/__init__.py
questioner/cli.py
questioner/demo.py
questioner/questioner.py
questioner-0.1.0.dist-info/AUTHORS.rst
questioner-0.1.0.dist-info/LICENSE
questioner-0.1.0.dist-info/METADATA
questioner-0.1.0.dist-info/WHEEL
questioner-0.1.0.dist-info/top_level.txt
questioner-0.1.0.dist-info/RECORD
