Metadata-Version: 2.1
Name: questioner
Version: 0.1.0
Summary: A lightweight  Python interface for annotating things.
Home-page: https://github.com/larsyencken/questioner
Author: Lars Yencken
Author-email: lars@yencken.org
License: MIT license
Keywords: questioner
Platform: UNKNOWN
Classifier: Development Status :: 2 - Pre-Alpha
Classifier: Intended Audience :: Developers
Classifier: License :: OSI Approved :: MIT License
Classifier: Natural Language :: English
Classifier: Programming Language :: Python :: 3
Classifier: Programming Language :: Python :: 3.7
Requires-Dist: readchar
Requires-Dist: blessings
